EveEN/ENall.py
EveEN/ENlogo.py
EveEN/ENplaysound.py
EveEN/ENweather.py
EveEN/ENweb.py
EveEN/__init__.py
EveEN/czy.py
EveEN/install.py
EveEN/pyaudio.py
Eve_EN-0.0.6.dist-info/LICENCE.txt
Eve_EN-0.0.6.dist-info/METADATA
Eve_EN-0.0.6.dist-info/WHEEL
Eve_EN-0.0.6.dist-info/top_level.txt
Eve_EN-0.0.6.dist-info/RECORD
