Metadata-Version: 2.1
Name: Eve-EN
Version: 0.0.6
Summary: This is AI (onl 3.10+).
Home-page: UNKNOWN
Author: F0X0000
Author-email: wcalenief0x@gmail.com
License: MIT
Keywords: Eve-EN,Ai,Eve,speechrecognition,EveEN
Platform: UNKNOWN
Classifier: Development Status :: 5 - Production/Stable
Classifier: Intended Audience :: Education
Classifier: Operating System :: Microsoft :: Windows :: Windows 10
Classifier: License :: OSI Approved :: MIT License
Classifier: Programming Language :: Python :: 3.10
License-File: LICENCE.txt
Requires-Dist: gtts
Requires-Dist: SpeechRecognition
Requires-Dist: beautifulsoup4
Requires-Dist: audio-py
